MANIFEST.in
README
setup.cfg
setup.py
dbgdb/__init__.py
dbgdb/cli.py
dbgdb/luigi.cfg
dbgdb.egg-info/PKG-INFO
dbgdb.egg-info/SOURCES.txt
dbgdb.egg-info/dependency_links.txt
dbgdb.egg-info/entry_points.txt
dbgdb.egg-info/requires.txt
dbgdb.egg-info/top_level.txt
dbgdb/db/__init__.py
dbgdb/db/postgres.json
dbgdb/db/postgres.py
dbgdb/ogr/__init__.py
dbgdb/ogr/postgres.py
dbgdb/targets/__init__.py
dbgdb/targets/postgres.py
dbgdb/tasks/__init__.py
dbgdb/tasks/postgres/__init__.py
dbgdb/tasks/postgres/drop.py
dbgdb/tasks/postgres/extract.py
dbgdb/tasks/postgres/load.py